{
  "_fv": 34,
  "_type": "rangeditem",
  "definition": {
    "renderType": 0,
    "texture": "thundershock",
    "customModelName": "Normal",
    "name": "Thundershock",
    "specialInfo": [],
    "creativeTab": {
      "value": "COMBAT"
    },
    "stackSize": 1,
    "ammoItem": {
      "value": "CUSTOM:ThunderBall"
    },
    "shootConstantly": false,
    "usageCount": 200,
    "actionSound": {
      "value": "CUSTOM:thundershock"
    },
    "hasGlow": false,
    "animation": "crossbow",
    "enableMeleeDamage": true,
    "damageVsEntity": 3.0,
    "bulletPower": 1.0,
    "bulletDamage": 5.0,
    "bulletKnockback": 5,
    "bulletParticles": false,
    "bulletIgnitesFire": false,
    "bulletItemTexture": {
      "value": "CUSTOM:ThunderBall"
    },
    "bulletModel": "Default",
    "customBulletModelTexture": "",
    "onBulletHitsBlock": {
      "name": "Shock"
    },
    "onBulletHitsPlayer": {
      "name": "Shock"
    },
    "onBulletHitsEntity": {
      "name": "Shock"
    }
  }
}